manifix/__init__.py
manifix/_version.py
manifix/check.py
manifix/command.py
manifix-1.1.1.dist-info/LICENSE.md
manifix-1.1.1.dist-info/METADATA
manifix-1.1.1.dist-info/WHEEL
manifix-1.1.1.dist-info/entry_points.txt
manifix-1.1.1.dist-info/top_level.txt
manifix-1.1.1.dist-info/RECORD
